jovyan_ai_jupyter_ext/_version.py
jovyan_ai_jupyter_ext/labextension/package.json
jovyan_ai_jupyter_ext/labextension/schemas/jovyan-ai-extension/package.json.orig
jovyan_ai_jupyter_ext/labextension/schemas/jovyan-ai-extension/plugin.json
jovyan_ai_jupyter_ext/labextension/static/101.c5c8687d9fe3acd46a1f.js
jovyan_ai_jupyter_ext/labextension/static/112.2c47ed1b33bf121e3381.js
jovyan_ai_jupyter_ext/labextension/static/181.5cb2f641d3144b07dba2.js
jovyan_ai_jupyter_ext/labextension/static/379.e8c196ff2d0e8a4bfadc.js
jovyan_ai_jupyter_ext/labextension/static/441.2fa27d75afc164c83169.js
jovyan_ai_jupyter_ext/labextension/static/493.4a601bce4eceae02ec9e.js
jovyan_ai_jupyter_ext/labextension/static/remoteEntry.bf4b4082a3c1fcd6335a.js
jovyan_ai_jupyter_ext/labextension/static/style.js
jovyan_ai_jupyter_ext/labextension/static/third-party-licenses.json
jovyan_ai_extension-0.1.0.data/data/share/jupyter/labextensions/jovyan-ai-extension/package.json
jovyan_ai_extension-0.1.0.data/data/share/jupyter/labextensions/jovyan-ai-extension/schemas/jovyan-ai-extension/package.json.orig
jovyan_ai_extension-0.1.0.data/data/share/jupyter/labextensions/jovyan-ai-extension/schemas/jovyan-ai-extension/plugin.json
jovyan_ai_extension-0.1.0.data/data/share/jupyter/labextensions/jovyan-ai-extension/static/101.c5c8687d9fe3acd46a1f.js
jovyan_ai_extension-0.1.0.data/data/share/jupyter/labextensions/jovyan-ai-extension/static/112.2c47ed1b33bf121e3381.js
jovyan_ai_extension-0.1.0.data/data/share/jupyter/labextensions/jovyan-ai-extension/static/181.5cb2f641d3144b07dba2.js
jovyan_ai_extension-0.1.0.data/data/share/jupyter/labextensions/jovyan-ai-extension/static/379.e8c196ff2d0e8a4bfadc.js
jovyan_ai_extension-0.1.0.data/data/share/jupyter/labextensions/jovyan-ai-extension/static/441.2fa27d75afc164c83169.js
jovyan_ai_extension-0.1.0.data/data/share/jupyter/labextensions/jovyan-ai-extension/static/493.4a601bce4eceae02ec9e.js
jovyan_ai_extension-0.1.0.dist-info/METADATA
jovyan_ai_extension-0.1.0.dist-info/WHEEL
jovyan_ai_extension-0.1.0.dist-info/licenses/LICENSE
jovyan_ai_extension-0.1.0.dist-info/RECORD
